pyzrpc/__init__.py
pyzrpc/run.py
pyzrpc/admin/__init__.py
pyzrpc/admin/admin_web.py
pyzrpc/admin/common.py
pyzrpc/admin/nodes.py
pyzrpc/admin/services.py
pyzrpc/admin/tasks.py
pyzrpc/admin/user_manual.py
pyzrpc/cipher/__init__.py
pyzrpc/cipher/cipher.py
pyzrpc/logger/__init__.py
pyzrpc/logger/logger.py
pyzrpc/meta/__init__.py
pyzrpc/meta/key.py
pyzrpc/meta/meta.py
pyzrpc/meta/observer.py
pyzrpc/mongo/__init__.py
pyzrpc/mongo/client.py
pyzrpc/nodes/__init__.py
pyzrpc/nodes/heartbeat_detection.py
pyzrpc/nodes/nodes.py
pyzrpc/observer/__init__.py
pyzrpc/observer/observer.py
pyzrpc/rabbit/__init__.py
pyzrpc/rabbit/rabbit.py
pyzrpc/service/__init__.py
pyzrpc/service/service_constructor.py
pyzrpc/service/service_start.py
pyzrpc/utils/__init__.py
pyzrpc/utils/rpc_proxy.py
pyzrpc/utils/utils.py
pyzrpc/work/__init__.py
pyzrpc/work/work_constructor.py
pyzrpc/work/work_start.py
pyzrpc-2.3.dist-info/LICENSE
pyzrpc-2.3.dist-info/METADATA
pyzrpc-2.3.dist-info/WHEEL
pyzrpc-2.3.dist-info/top_level.txt
pyzrpc-2.3.dist-info/RECORD
