Metadata-Version: 2.1
Name: pyzrpc
Version: 2.3
Summary: pyzrpc
Home-page: https://gitee.com/ZYPH/zerorpc
Author: YanPing
Author-email: zyphhxx@foxmail.com
Maintainer: YanPing
Maintainer-email: zyphhxx@foxmail.com
License: MIT License
Platform: UNKNOWN
Classifier: Development Status :: 3 - Alpha
Classifier: Intended Audience :: Developers
Classifier: Topic :: Software Development :: Build Tools
Classifier: License :: OSI Approved :: MIT License
Classifier: Programming Language :: Python :: 3
Requires-Python: >=3.7,<3.11
License-File: LICENSE
Requires-Dist: nameko (==2.14.1)
Requires-Dist: pika (==1.3.2)
Requires-Dist: pytz (>=2024.1)
Requires-Dist: pymongo (==4.8.0)
Requires-Dist: kombu (==5.4.0)
Requires-Dist: pycryptodomex (==3.14.1)
Requires-Dist: streamlit (==1.40.1)
